pyrializer/__init__.py
pyrializer/decode.py
pyrializer/encode.py
pyrializer/exceptions.py
pyrializer/types/__init__.py
pyrializer/types/builtin.py
pyrializer/util.py
pyrializer-0.2.0.dist-info/WHEEL
pyrializer-0.2.0.dist-info/METADATA
pyrializer-0.2.0.dist-info/RECORD
