Metadata-Version: 2.1
Name: pyrializer
Version: 0.2.0
Summary: A Python object (de)serializer
Home-page: https://github.com/superruzafa/pyrializer
Author: Alfonso Ruzafa
Author-email: alfonso.ruzafa@movo.me
Requires-Python: >=3.7,<4.0
Classifier: Programming Language :: Python :: 3
Classifier: Programming Language :: Python :: 3.7
Classifier: Programming Language :: Python :: 3.8
Project-URL: Repository, https://github.com/superruzafa/pyrializer
